trinity_agent_monitoring/MCP_monitor.py
trinity_agent_monitoring/__init__.py
trinity_agent_monitoring/agent_monitor.py
trinity_agent_monitoring-0.1.4.dist-info/METADATA
trinity_agent_monitoring-0.1.4.dist-info/WHEEL
trinity_agent_monitoring-0.1.4.dist-info/top_level.txt
trinity_agent_monitoring-0.1.4.dist-info/RECORD
