Metadata-Version: 2.4
Name: trinity-agent-monitoring
Version: 0.1.4
Summary: A Python SDK for Trinity Agent Monitoring API
Home-page: https://github.com/roosterhr/gg-trinity-agent-monitoring-sdk
Author: Team Trinity
Author-email: support@giggso.com
Classifier: Programming Language :: Python :: 3
Classifier: Programming Language :: Python :: 3.10
Classifier: License :: OSI Approved :: MIT License
Classifier: Operating System :: OS Independent
Requires-Python: >=3.11
Requires-Dist: langfuse==3.2.1
Requires-Dist: mcp-use==1.3.7
Dynamic: author
Dynamic: author-email
Dynamic: classifier
Dynamic: description
Dynamic: description-content-type
Dynamic: home-page
Dynamic: requires-dist
Dynamic: requires-python
Dynamic: summary
